{
  "_format": "hh-sol-cache-2",
  "files": {
    "/Users/johnk/demos/Fahom_Hackathon/on-chain/contracts/Cryrdle.sol": {
      "lastModificationDate": 1676825018557,
      "contentHash": "373bbc0212b83ab3bcecb18e48e64453",
      "sourceName": "contracts/Cryrdle.sol",
      "solcConfig": {
        "version": "0.8.7",
        "settings": {
          "optimizer": {
            "enabled": false,
            "runs": 200
          },
          "outputSelection": {
            "*": {
              "*": [
                "abi",
                "evm.bytecode",
                "evm.deployedBytecode",
                "evm.methodIdentifiers",
                "metadata",
                "devdoc",
                "userdoc",
                "storageLayout",
                "evm.gasEstimates"
              ],
              "": [
                "ast"
              ]
            }
          },
          "metadata": {
            "useLiteralContent": true
          }
        }
      },
      "imports": [
        "@chainlink/contracts/src/v0.8/interfaces/VRFCoordinatorV2Interface.sol",
        "@chainlink/contracts/src/v0.8/VRFConsumerBaseV2.sol",
        "@chainlink/contracts/src/v0.8/interfaces/AutomationCompatibleInterface.sol",
        "hardhat/console.sol"
      ],
      "versionPragmas": [
        "0.8.7"
      ],
      "artifacts": [
        "Cryrdle"
      ]
    },
    "/Users/johnk/demos/Fahom_Hackathon/on-chain/node_modules/hardhat/console.sol": {
      "lastModificationDate": 1676115645599,
      "contentHash": "4ff3cd2f6272c9a6516e9ee4f2b967d3",
      "sourceName": "hardhat/console.sol",
      "solcConfig": {
        "version": "0.8.7",
        "settings": {
          "optimizer": {
            "enabled": false,
            "runs": 200
          },
          "outputSelection": {
            "*": {
              "*": [
                "abi",
                "evm.bytecode",
                "evm.deployedBytecode",
                "evm.methodIdentifiers",
                "metadata",
                "devdoc",
                "userdoc",
                "storageLayout",
                "evm.gasEstimates"
              ],
              "": [
                "ast"
              ]
            }
          },
          "metadata": {
            "useLiteralContent": true
          }
        }
      },
      "imports": [],
      "versionPragmas": [
        ">= 0.4.22 <0.9.0"
      ],
      "artifacts": [
        "console"
      ]
    },
    "/Users/johnk/demos/Fahom_Hackathon/on-chain/node_modules/@chainlink/contracts/src/v0.8/VRFConsumerBaseV2.sol": {
      "lastModificationDate": 1676732792502,
      "contentHash": "eb9cc526ef59dfc4d644f56ddca0633a",
      "sourceName": "@chainlink/contracts/src/v0.8/VRFConsumerBaseV2.sol",
      "solcConfig": {
        "version": "0.8.7",
        "settings": {
          "optimizer": {
            "enabled": false,
            "runs": 200
          },
          "outputSelection": {
            "*": {
              "*": [
                "abi",
                "evm.bytecode",
                "evm.deployedBytecode",
                "evm.methodIdentifiers",
                "metadata",
                "devdoc",
                "userdoc",
                "storageLayout",
                "evm.gasEstimates"
              ],
              "": [
                "ast"
              ]
            }
          },
          "metadata": {
            "useLiteralContent": true
          }
        }
      },
      "imports": [],
      "versionPragmas": [
        "^0.8.4"
      ],
      "artifacts": [
        "VRFConsumerBaseV2"
      ]
    },
    "/Users/johnk/demos/Fahom_Hackathon/on-chain/node_modules/@chainlink/contracts/src/v0.8/interfaces/VRFCoordinatorV2Interface.sol": {
      "lastModificationDate": 1676732792895,
      "contentHash": "8c9ed3426b676f67ee200a2bec96e224",
      "sourceName": "@chainlink/contracts/src/v0.8/interfaces/VRFCoordinatorV2Interface.sol",
      "solcConfig": {
        "version": "0.8.7",
        "settings": {
          "optimizer": {
            "enabled": false,
            "runs": 200
          },
          "outputSelection": {
            "*": {
              "*": [
                "abi",
                "evm.bytecode",
                "evm.deployedBytecode",
                "evm.methodIdentifiers",
                "metadata",
                "devdoc",
                "userdoc",
                "storageLayout",
                "evm.gasEstimates"
              ],
              "": [
                "ast"
              ]
            }
          },
          "metadata": {
            "useLiteralContent": true
          }
        }
      },
      "imports": [],
      "versionPragmas": [
        "^0.8.0"
      ],
      "artifacts": [
        "VRFCoordinatorV2Interface"
      ]
    },
    "/Users/johnk/demos/Fahom_Hackathon/on-chain/node_modules/@chainlink/contracts/src/v0.8/interfaces/AutomationCompatibleInterface.sol": {
      "lastModificationDate": 1676732792893,
      "contentHash": "c52969cee392918edbf23f914e01c0dc",
      "sourceName": "@chainlink/contracts/src/v0.8/interfaces/AutomationCompatibleInterface.sol",
      "solcConfig": {
        "version": "0.8.7",
        "settings": {
          "optimizer": {
            "enabled": false,
            "runs": 200
          },
          "outputSelection": {
            "*": {
              "*": [
                "abi",
                "evm.bytecode",
                "evm.deployedBytecode",
                "evm.methodIdentifiers",
                "metadata",
                "devdoc",
                "userdoc",
                "storageLayout",
                "evm.gasEstimates"
              ],
              "": [
                "ast"
              ]
            }
          },
          "metadata": {
            "useLiteralContent": true
          }
        }
      },
      "imports": [],
      "versionPragmas": [
        "^0.8.0"
      ],
      "artifacts": [
        "AutomationCompatibleInterface"
      ]
    },
    "/Users/johnk/demos/Fahom_Hackathon/on-chain/contracts/VRFv2Consumer.sol": {
      "lastModificationDate": 1676732099137,
      "contentHash": "534ab7f70736f09c35eef149a6ee8e71",
      "sourceName": "contracts/VRFv2Consumer.sol",
      "solcConfig": {
        "version": "0.8.7",
        "settings": {
          "optimizer": {
            "enabled": false,
            "runs": 200
          },
          "outputSelection": {
            "*": {
              "*": [
                "abi",
                "evm.bytecode",
                "evm.deployedBytecode",
                "evm.methodIdentifiers",
                "metadata",
                "devdoc",
                "userdoc",
                "storageLayout",
                "evm.gasEstimates"
              ],
              "": [
                "ast"
              ]
            }
          },
          "metadata": {
            "useLiteralContent": true
          }
        }
      },
      "imports": [
        "@chainlink/contracts/src/v0.8/interfaces/VRFCoordinatorV2Interface.sol",
        "@chainlink/contracts/src/v0.8/VRFConsumerBaseV2.sol",
        "@chainlink/contracts/src/v0.8/ConfirmedOwner.sol"
      ],
      "versionPragmas": [
        "^0.8.7"
      ],
      "artifacts": [
        "VRFv2Consumer"
      ]
    },
    "/Users/johnk/demos/Fahom_Hackathon/on-chain/node_modules/@chainlink/contracts/src/v0.8/ConfirmedOwner.sol": {
      "lastModificationDate": 1676732792501,
      "contentHash": "16d64572b0310127fc8a771e63be6d20",
      "sourceName": "@chainlink/contracts/src/v0.8/ConfirmedOwner.sol",
      "solcConfig": {
        "version": "0.8.7",
        "settings": {
          "optimizer": {
            "enabled": false,
            "runs": 200
          },
          "outputSelection": {
            "*": {
              "*": [
                "abi",
                "evm.bytecode",
                "evm.deployedBytecode",
                "evm.methodIdentifiers",
                "metadata",
                "devdoc",
                "userdoc",
                "storageLayout",
                "evm.gasEstimates"
              ],
              "": [
                "ast"
              ]
            }
          },
          "metadata": {
            "useLiteralContent": true
          }
        }
      },
      "imports": [
        "./ConfirmedOwnerWithProposal.sol"
      ],
      "versionPragmas": [
        "^0.8.0"
      ],
      "artifacts": [
        "ConfirmedOwner"
      ]
    },
    "/Users/johnk/demos/Fahom_Hackathon/on-chain/node_modules/@chainlink/contracts/src/v0.8/ConfirmedOwnerWithProposal.sol": {
      "lastModificationDate": 1676732792501,
      "contentHash": "8b1c5f02622cd87472493bda6595d1be",
      "sourceName": "@chainlink/contracts/src/v0.8/ConfirmedOwnerWithProposal.sol",
      "solcConfig": {
        "version": "0.8.7",
        "settings": {
          "optimizer": {
            "enabled": false,
            "runs": 200
          },
          "outputSelection": {
            "*": {
              "*": [
                "abi",
                "evm.bytecode",
                "evm.deployedBytecode",
                "evm.methodIdentifiers",
                "metadata",
                "devdoc",
                "userdoc",
                "storageLayout",
                "evm.gasEstimates"
              ],
              "": [
                "ast"
              ]
            }
          },
          "metadata": {
            "useLiteralContent": true
          }
        }
      },
      "imports": [
        "./interfaces/OwnableInterface.sol"
      ],
      "versionPragmas": [
        "^0.8.0"
      ],
      "artifacts": [
        "ConfirmedOwnerWithProposal"
      ]
    },
    "/Users/johnk/demos/Fahom_Hackathon/on-chain/node_modules/@chainlink/contracts/src/v0.8/interfaces/OwnableInterface.sol": {
      "lastModificationDate": 1676732792895,
      "contentHash": "2e814c8a9f77897f6995436d97c23d99",
      "sourceName": "@chainlink/contracts/src/v0.8/interfaces/OwnableInterface.sol",
      "solcConfig": {
        "version": "0.8.7",
        "settings": {
          "optimizer": {
            "enabled": false,
            "runs": 200
          },
          "outputSelection": {
            "*": {
              "*": [
                "abi",
                "evm.bytecode",
                "evm.deployedBytecode",
                "evm.methodIdentifiers",
                "metadata",
                "devdoc",
                "userdoc",
                "storageLayout",
                "evm.gasEstimates"
              ],
              "": [
                "ast"
              ]
            }
          },
          "metadata": {
            "useLiteralContent": true
          }
        }
      },
      "imports": [],
      "versionPragmas": [
        "^0.8.0"
      ],
      "artifacts": [
        "OwnableInterface"
      ]
    }
  }
}
